lzf.cp37-win_amd64.pyd
python_lzf_e-0.2.5.dist-info/LICENSE
python_lzf_e-0.2.5.dist-info/METADATA
python_lzf_e-0.2.5.dist-info/WHEEL
python_lzf_e-0.2.5.dist-info/top_level.txt
python_lzf_e-0.2.5.dist-info/RECORD
