Metadata-Version: 2.1
Name: python-lzf-e
Version: 0.2.5
Summary: C Extension for liblzf
Home-page: http://github.com/teepark/python-lzf
Author: Travis Parker
Author-email: travis.parker@gmail.com
License: BSD
Platform: UNKNOWN
Classifier: Development Status :: 4 - Beta
Classifier: Intended Audience :: Developers
Classifier: License :: OSI Approved :: BSD License
Classifier: Natural Language :: English
Classifier: Programming Language :: C
Classifier: Topic :: System :: Archiving :: Compression
